{"match_id": "16d42f47-7a8f-4b42-9e91-09f4d8be3a2f.nakama-0", "map_id": "Lockdown", "date": "February 11", "events": [{"player": "a0738c7c-612e-45c9-b24d-057115642057", "is_human": true, "type": "Position", "ts": 1770769742, "px": 157.17, "py": 371.78}, {"player": "a0738c7c-612e-45c9-b24d-057115642057", "is_human": true, "type": "Position", "ts": 1770769763, "px": 155.96, "py": 383.18}, {"player": "a0738c7c-612e-45c9-b24d-057115642057", "is_human": true, "type": "Position", "ts": 1770769768, "px": 163.63, "py": 388.02}, {"player": "a0738c7c-612e-45c9-b24d-057115642057", "is_human": true, "type": "Position", "ts": 1770769778, "px": 176.29, "py": 406.1}, {"player": "a0738c7c-612e-45c9-b24d-057115642057", "is_human": true, "type": "Position", "ts": 1770769783, "px": 197.76, "py": 394.71}, {"player": "a0738c7c-612e-45c9-b24d-057115642057", "is_human": true, "type": "Position", "ts": 1770769788, "px": 195.89, "py": 383.94}, {"player": "a0738c7c-612e-45c9-b24d-057115642057", "is_human": true, "type": "Position", "ts": 1770769793, "px": 195.79, "py": 385.49}, {"player": "a0738c7c-612e-45c9-b24d-057115642057", "is_human": true, "type": "Position", "ts": 1770769798, "px": 197.43, "py": 374.69}, {"player": "a0738c7c-612e-45c9-b24d-057115642057", "is_human": true, "type": "Position", "ts": 1770769803, "px": 212.68, "py": 368.39}, {"player": "a0738c7c-612e-45c9-b24d-057115642057", "is_human": true, "type": "Loot", "ts": 1770769805, "px": 210.11, "py": 375.74}, {"player": "a0738c7c-612e-45c9-b24d-057115642057", "is_human": true, "type": "Position", "ts": 1770769808, "px": 212.88, "py": 374.98}, {"player": "a0738c7c-612e-45c9-b24d-057115642057", "is_human": true, "type": "Position", "ts": 1770769813, "px": 223.49, "py": 378.26}, {"player": "a0738c7c-612e-45c9-b24d-057115642057", "is_human": true, "type": "Position", "ts": 1770769818, "px": 221.16, "py": 395.59}, {"player": "a0738c7c-612e-45c9-b24d-057115642057", "is_human": true, "type": "Position", "ts": 1770769823, "px": 211.96, "py": 398.47}, {"player": "a0738c7c-612e-45c9-b24d-057115642057", "is_human": true, "type": "Position", "ts": 1770769828, "px": 215.88, "py": 408.26}, {"player": "a0738c7c-612e-45c9-b24d-057115642057", "is_human": true, "type": "Position", "ts": 1770769833, "px": 220.08, "py": 419.54}, {"player": "a0738c7c-612e-45c9-b24d-057115642057", "is_human": true, "type": "Position", "ts": 1770769838, "px": 219.34, "py": 419.94}, {"player": "a0738c7c-612e-45c9-b24d-057115642057", "is_human": true, "type": "Position", "ts": 1770769843, "px": 210.22, "py": 422.4}, {"player": "a0738c7c-612e-45c9-b24d-057115642057", "is_human": true, "type": "Position", "ts": 1770769848, "px": 213.72, "py": 448.32}, {"player": "a0738c7c-612e-45c9-b24d-057115642057", "is_human": true, "type": "Position", "ts": 1770769853, "px": 212.22, "py": 455.87}, {"player": "a0738c7c-612e-45c9-b24d-057115642057", "is_human": true, "type": "Loot", "ts": 1770769854, "px": 212.22, "py": 455.87}, {"player": "a0738c7c-612e-45c9-b24d-057115642057", "is_human": true, "type": "Position", "ts": 1770769858, "px": 218.11, "py": 455.35}, {"player": "a0738c7c-612e-45c9-b24d-057115642057", "is_human": true, "type": "Position", "ts": 1770769863, "px": 204.98, "py": 454.78}, {"player": "a0738c7c-612e-45c9-b24d-057115642057", "is_human": true, "type": "Position", "ts": 1770769868, "px": 199.9, "py": 457.0}, {"player": "a0738c7c-612e-45c9-b24d-057115642057", "is_human": true, "type": "Position", "ts": 1770769873, "px": 214.29, "py": 443.85}, {"player": "a0738c7c-612e-45c9-b24d-057115642057", "is_human": true, "type": "Position", "ts": 1770769878, "px": 236.57, "py": 448.54}, {"player": "a0738c7c-612e-45c9-b24d-057115642057", "is_human": true, "type": "Position", "ts": 1770769883, "px": 229.58, "py": 473.59}, {"player": "a0738c7c-612e-45c9-b24d-057115642057", "is_human": true, "type": "Position", "ts": 1770769888, "px": 215.13, "py": 500.87}, {"player": "a0738c7c-612e-45c9-b24d-057115642057", "is_human": true, "type": "Position", "ts": 1770769893, "px": 196.21, "py": 507.27}, {"player": "a0738c7c-612e-45c9-b24d-057115642057", "is_human": true, "type": "BotKill", "ts": 1770769898, "px": 183.6, "py": 509.83}, {"player": "a0738c7c-612e-45c9-b24d-057115642057", "is_human": true, "type": "Position", "ts": 1770769898, "px": 182.79, "py": 509.95}, {"player": "a0738c7c-612e-45c9-b24d-057115642057", "is_human": true, "type": "Position", "ts": 1770769903, "px": 167.15, "py": 516.92}, {"player": "a0738c7c-612e-45c9-b24d-057115642057", "is_human": true, "type": "Position", "ts": 1770769908, "px": 146.98, "py": 516.88}, {"player": "a0738c7c-612e-45c9-b24d-057115642057", "is_human": true, "type": "Position", "ts": 1770769913, "px": 125.16, "py": 525.52}, {"player": "a0738c7c-612e-45c9-b24d-057115642057", "is_human": true, "type": "Loot", "ts": 1770769914, "px": 125.16, "py": 525.52}, {"player": "a0738c7c-612e-45c9-b24d-057115642057", "is_human": true, "type": "Position", "ts": 1770769918, "px": 132.42, "py": 544.43}, {"player": "a0738c7c-612e-45c9-b24d-057115642057", "is_human": true, "type": "Position", "ts": 1770769923, "px": 158.07, "py": 556.17}, {"player": "a0738c7c-612e-45c9-b24d-057115642057", "is_human": true, "type": "Position", "ts": 1770769928, "px": 184.42, "py": 569.98}, {"player": "a0738c7c-612e-45c9-b24d-057115642057", "is_human": true, "type": "Position", "ts": 1770769933, "px": 209.08, "py": 586.4}, {"player": "a0738c7c-612e-45c9-b24d-057115642057", "is_human": true, "type": "Position", "ts": 1770769939, "px": 207.73, "py": 608.9}, {"player": "a0738c7c-612e-45c9-b24d-057115642057", "is_human": true, "type": "Position", "ts": 1770769944, "px": 199.67, "py": 618.71}, {"player": "a0738c7c-612e-45c9-b24d-057115642057", "is_human": true, "type": "Position", "ts": 1770769949, "px": 201.34, "py": 627.04}, {"player": "a0738c7c-612e-45c9-b24d-057115642057", "is_human": true, "type": "Loot", "ts": 1770769949, "px": 201.34, "py": 627.04}, {"player": "a0738c7c-612e-45c9-b24d-057115642057", "is_human": true, "type": "Position", "ts": 1770769954, "px": 209.95, "py": 631.14}, {"player": "a0738c7c-612e-45c9-b24d-057115642057", "is_human": true, "type": "Loot", "ts": 1770769954, "px": 210.04, "py": 631.17}, {"player": "a0738c7c-612e-45c9-b24d-057115642057", "is_human": true, "type": "Position", "ts": 1770769964, "px": 211.59, "py": 625.13}, {"player": "a0738c7c-612e-45c9-b24d-057115642057", "is_human": true, "type": "Position", "ts": 1770769969, "px": 214.21, "py": 619.89}, {"player": "a0738c7c-612e-45c9-b24d-057115642057", "is_human": true, "type": "Position", "ts": 1770769974, "px": 195.77, "py": 621.17}, {"player": "a0738c7c-612e-45c9-b24d-057115642057", "is_human": true, "type": "Position", "ts": 1770769979, "px": 192.66, "py": 629.53}, {"player": "a0738c7c-612e-45c9-b24d-057115642057", "is_human": true, "type": "Position", "ts": 1770769984, "px": 209.21, "py": 633.78}, {"player": "a0738c7c-612e-45c9-b24d-057115642057", "is_human": true, "type": "Loot", "ts": 1770769986, "px": 209.21, "py": 633.78}, {"player": "a0738c7c-612e-45c9-b24d-057115642057", "is_human": true, "type": "Position", "ts": 1770769989, "px": 209.5, "py": 640.39}, {"player": "a0738c7c-612e-45c9-b24d-057115642057", "is_human": true, "type": "Position", "ts": 1770769994, "px": 215.76, "py": 648.38}, {"player": "a0738c7c-612e-45c9-b24d-057115642057", "is_human": true, "type": "Position", "ts": 1770769999, "px": 224.03, "py": 655.93}, {"player": "a0738c7c-612e-45c9-b24d-057115642057", "is_human": true, "type": "Position", "ts": 1770770004, "px": 239.46, "py": 664.56}, {"player": "a0738c7c-612e-45c9-b24d-057115642057", "is_human": true, "type": "Position", "ts": 1770770009, "px": 264.5, "py": 673.4}, {"player": "a0738c7c-612e-45c9-b24d-057115642057", "is_human": true, "type": "Position", "ts": 1770770014, "px": 291.14, "py": 678.09}, {"player": "a0738c7c-612e-45c9-b24d-057115642057", "is_human": true, "type": "Position", "ts": 1770770019, "px": 309.09, "py": 682.52}, {"player": "a0738c7c-612e-45c9-b24d-057115642057", "is_human": true, "type": "Position", "ts": 1770770024, "px": 311.49, "py": 688.65}, {"player": "a0738c7c-612e-45c9-b24d-057115642057", "is_human": true, "type": "Position", "ts": 1770770029, "px": 318.47, "py": 693.53}, {"player": "a0738c7c-612e-45c9-b24d-057115642057", "is_human": true, "type": "Position", "ts": 1770770034, "px": 318.59, "py": 685.88}, {"player": "a0738c7c-612e-45c9-b24d-057115642057", "is_human": true, "type": "BotKill", "ts": 1770770038, "px": 315.09, "py": 691.32}, {"player": "a0738c7c-612e-45c9-b24d-057115642057", "is_human": true, "type": "Position", "ts": 1770770039, "px": 313.5, "py": 692.99}, {"player": "a0738c7c-612e-45c9-b24d-057115642057", "is_human": true, "type": "Position", "ts": 1770770044, "px": 310.62, "py": 703.38}, {"player": "a0738c7c-612e-45c9-b24d-057115642057", "is_human": true, "type": "Position", "ts": 1770770049, "px": 333.55, "py": 708.72}, {"player": "a0738c7c-612e-45c9-b24d-057115642057", "is_human": true, "type": "Position", "ts": 1770770054, "px": 333.5, "py": 694.0}, {"player": "a0738c7c-612e-45c9-b24d-057115642057", "is_human": true, "type": "Position", "ts": 1770770059, "px": 340.87, "py": 698.55}, {"player": "a0738c7c-612e-45c9-b24d-057115642057", "is_human": true, "type": "Loot", "ts": 1770770061, "px": 340.87, "py": 698.55}, {"player": "a0738c7c-612e-45c9-b24d-057115642057", "is_human": true, "type": "Position", "ts": 1770770064, "px": 337.45, "py": 704.62}, {"player": "a0738c7c-612e-45c9-b24d-057115642057", "is_human": true, "type": "Position", "ts": 1770770069, "px": 329.23, "py": 701.47}, {"player": "a0738c7c-612e-45c9-b24d-057115642057", "is_human": true, "type": "Position", "ts": 1770770074, "px": 343.43, "py": 693.57}, {"player": "a0738c7c-612e-45c9-b24d-057115642057", "is_human": true, "type": "Position", "ts": 1770770079, "px": 350.27, "py": 677.43}, {"player": "a0738c7c-612e-45c9-b24d-057115642057", "is_human": true, "type": "Position", "ts": 1770770084, "px": 337.38, "py": 654.37}, {"player": "a0738c7c-612e-45c9-b24d-057115642057", "is_human": true, "type": "BotKill", "ts": 1770770088, "px": 333.53, "py": 646.41}, {"player": "a0738c7c-612e-45c9-b24d-057115642057", "is_human": true, "type": "Position", "ts": 1770770089, "px": 333.53, "py": 646.41}, {"player": "a0738c7c-612e-45c9-b24d-057115642057", "is_human": true, "type": "Position", "ts": 1770770099, "px": 326.58, "py": 651.97}, {"player": "a0738c7c-612e-45c9-b24d-057115642057", "is_human": true, "type": "Position", "ts": 1770770104, "px": 325.86, "py": 647.5}, {"player": "a0738c7c-612e-45c9-b24d-057115642057", "is_human": true, "type": "Position", "ts": 1770770109, "px": 324.7, "py": 640.28}, {"player": "a0738c7c-612e-45c9-b24d-057115642057", "is_human": true, "type": "Position", "ts": 1770770115, "px": 316.36, "py": 630.11}, {"player": "a0738c7c-612e-45c9-b24d-057115642057", "is_human": true, "type": "Loot", "ts": 1770770117, "px": 310.93, "py": 629.28}, {"player": "a0738c7c-612e-45c9-b24d-057115642057", "is_human": true, "type": "Position", "ts": 1770770120, "px": 312.05, "py": 628.65}, {"player": "a0738c7c-612e-45c9-b24d-057115642057", "is_human": true, "type": "Position", "ts": 1770770125, "px": 316.15, "py": 619.69}, {"player": "a0738c7c-612e-45c9-b24d-057115642057", "is_human": true, "type": "Position", "ts": 1770770130, "px": 320.04, "py": 613.89}, {"player": "a0738c7c-612e-45c9-b24d-057115642057", "is_human": true, "type": "Position", "ts": 1770770135, "px": 337.98, "py": 609.21}, {"player": "a0738c7c-612e-45c9-b24d-057115642057", "is_human": true, "type": "Loot", "ts": 1770770136, "px": 337.98, "py": 609.21}, {"player": "a0738c7c-612e-45c9-b24d-057115642057", "is_human": true, "type": "Loot", "ts": 1770770137, "px": 337.98, "py": 609.21}, {"player": "a0738c7c-612e-45c9-b24d-057115642057", "is_human": true, "type": "Position", "ts": 1770770140, "px": 330.71, "py": 603.81}, {"player": "a0738c7c-612e-45c9-b24d-057115642057", "is_human": true, "type": "Position", "ts": 1770770145, "px": 314.97, "py": 580.07}, {"player": "a0738c7c-612e-45c9-b24d-057115642057", "is_human": true, "type": "Position", "ts": 1770770150, "px": 313.76, "py": 576.37}, {"player": "a0738c7c-612e-45c9-b24d-057115642057", "is_human": true, "type": "Position", "ts": 1770770155, "px": 320.43, "py": 580.51}, {"player": "a0738c7c-612e-45c9-b24d-057115642057", "is_human": true, "type": "Position", "ts": 1770770160, "px": 329.54, "py": 582.95}, {"player": "a0738c7c-612e-45c9-b24d-057115642057", "is_human": true, "type": "Position", "ts": 1770770165, "px": 325.1, "py": 579.16}, {"player": "a0738c7c-612e-45c9-b24d-057115642057", "is_human": true, "type": "Position", "ts": 1770770170, "px": 337.68, "py": 576.22}, {"player": "a0738c7c-612e-45c9-b24d-057115642057", "is_human": true, "type": "Loot", "ts": 1770770173, "px": 338.28, "py": 576.88}, {"player": "a0738c7c-612e-45c9-b24d-057115642057", "is_human": true, "type": "Position", "ts": 1770770180, "px": 335.08, "py": 567.11}, {"player": "a0738c7c-612e-45c9-b24d-057115642057", "is_human": true, "type": "Position", "ts": 1770770185, "px": 355.02, "py": 583.38}, {"player": "a0738c7c-612e-45c9-b24d-057115642057", "is_human": true, "type": "Position", "ts": 1770770190, "px": 371.62, "py": 601.59}, {"player": "a0738c7c-612e-45c9-b24d-057115642057", "is_human": true, "type": "Position", "ts": 1770770195, "px": 360.0, "py": 617.08}, {"player": "a0738c7c-612e-45c9-b24d-057115642057", "is_human": true, "type": "Position", "ts": 1770770200, "px": 362.82, "py": 626.83}, {"player": "a0738c7c-612e-45c9-b24d-057115642057", "is_human": true, "type": "Position", "ts": 1770770205, "px": 352.15, "py": 631.96}, {"player": "a0738c7c-612e-45c9-b24d-057115642057", "is_human": true, "type": "Position", "ts": 1770770210, "px": 358.41, "py": 615.75}, {"player": "a0738c7c-612e-45c9-b24d-057115642057", "is_human": true, "type": "Position", "ts": 1770770215, "px": 357.54, "py": 616.83}, {"player": "a0738c7c-612e-45c9-b24d-057115642057", "is_human": true, "type": "Position", "ts": 1770770220, "px": 357.61, "py": 620.81}, {"player": "a0738c7c-612e-45c9-b24d-057115642057", "is_human": true, "type": "Position", "ts": 1770770225, "px": 357.21, "py": 618.69}, {"player": "a0738c7c-612e-45c9-b24d-057115642057", "is_human": true, "type": "BotKill", "ts": 1770770229, "px": 358.0, "py": 614.92}, {"player": "a0738c7c-612e-45c9-b24d-057115642057", "is_human": true, "type": "Position", "ts": 1770770235, "px": 365.19, "py": 611.26}, {"player": "a0738c7c-612e-45c9-b24d-057115642057", "is_human": true, "type": "Loot", "ts": 1770770239, "px": 356.02, "py": 594.42}, {"player": "a0738c7c-612e-45c9-b24d-057115642057", "is_human": true, "type": "Position", "ts": 1770770240, "px": 356.29, "py": 591.88}, {"player": "a0738c7c-612e-45c9-b24d-057115642057", "is_human": true, "type": "Position", "ts": 1770770245, "px": 369.92, "py": 566.71}, {"player": "a0738c7c-612e-45c9-b24d-057115642057", "is_human": true, "type": "Position", "ts": 1770770250, "px": 398.47, "py": 554.07}, {"player": "a0738c7c-612e-45c9-b24d-057115642057", "is_human": true, "type": "Position", "ts": 1770770255, "px": 421.9, "py": 542.76}, {"player": "a0738c7c-612e-45c9-b24d-057115642057", "is_human": true, "type": "Position", "ts": 1770770265, "px": 428.66, "py": 525.18}, {"player": "a0738c7c-612e-45c9-b24d-057115642057", "is_human": true, "type": "Position", "ts": 1770770270, "px": 430.56, "py": 524.66}, {"player": "a0738c7c-612e-45c9-b24d-057115642057", "is_human": true, "type": "BotKill", "ts": 1770770274, "px": 432.13, "py": 519.47}, {"player": "a0738c7c-612e-45c9-b24d-057115642057", "is_human": true, "type": "Position", "ts": 1770770275, "px": 433.45, "py": 518.51}, {"player": "a0738c7c-612e-45c9-b24d-057115642057", "is_human": true, "type": "Position", "ts": 1770770280, "px": 445.38, "py": 506.18}, {"player": "a0738c7c-612e-45c9-b24d-057115642057", "is_human": true, "type": "Loot", "ts": 1770770282, "px": 449.96, "py": 501.09}, {"player": "a0738c7c-612e-45c9-b24d-057115642057", "is_human": true, "type": "Loot", "ts": 1770770283, "px": 449.96, "py": 501.09}, {"player": "a0738c7c-612e-45c9-b24d-057115642057", "is_human": true, "type": "Position", "ts": 1770770285, "px": 454.24, "py": 490.7}, {"player": "a0738c7c-612e-45c9-b24d-057115642057", "is_human": true, "type": "Position", "ts": 1770770291, "px": 447.56, "py": 464.92}, {"player": "a0738c7c-612e-45c9-b24d-057115642057", "is_human": true, "type": "Loot", "ts": 1770770295, "px": 443.51, "py": 455.1}, {"player": "a0738c7c-612e-45c9-b24d-057115642057", "is_human": true, "type": "Position", "ts": 1770770296, "px": 443.31, "py": 454.88}, {"player": "a0738c7c-612e-45c9-b24d-057115642057", "is_human": true, "type": "Position", "ts": 1770770301, "px": 442.35, "py": 433.18}, {"player": "a0738c7c-612e-45c9-b24d-057115642057", "is_human": true, "type": "Position", "ts": 1770770306, "px": 430.6, "py": 417.2}, {"player": "a0738c7c-612e-45c9-b24d-057115642057", "is_human": true, "type": "Position", "ts": 1770770311, "px": 424.32, "py": 393.66}, {"player": "a0738c7c-612e-45c9-b24d-057115642057", "is_human": true, "type": "Position", "ts": 1770770316, "px": 435.49, "py": 379.92}, {"player": "a0738c7c-612e-45c9-b24d-057115642057", "is_human": true, "type": "Position", "ts": 1770770321, "px": 440.08, "py": 371.18}, {"player": "a0738c7c-612e-45c9-b24d-057115642057", "is_human": true, "type": "Position", "ts": 1770770326, "px": 446.77, "py": 346.44}, {"player": "a0738c7c-612e-45c9-b24d-057115642057", "is_human": true, "type": "Position", "ts": 1770770331, "px": 467.99, "py": 330.61}, {"player": "a0738c7c-612e-45c9-b24d-057115642057", "is_human": true, "type": "Position", "ts": 1770770336, "px": 482.2, "py": 314.32}, {"player": "a0738c7c-612e-45c9-b24d-057115642057", "is_human": true, "type": "Position", "ts": 1770770341, "px": 481.45, "py": 300.64}, {"player": "a0738c7c-612e-45c9-b24d-057115642057", "is_human": true, "type": "Position", "ts": 1770770346, "px": 490.36, "py": 298.27}, {"player": "a0738c7c-612e-45c9-b24d-057115642057", "is_human": true, "type": "Loot", "ts": 1770770349, "px": 493.83, "py": 299.05}, {"player": "a0738c7c-612e-45c9-b24d-057115642057", "is_human": true, "type": "Position", "ts": 1770770351, "px": 493.68, "py": 298.06}, {"player": "a0738c7c-612e-45c9-b24d-057115642057", "is_human": true, "type": "Position", "ts": 1770770356, "px": 494.4, "py": 282.61}, {"player": "a0738c7c-612e-45c9-b24d-057115642057", "is_human": true, "type": "Position", "ts": 1770770361, "px": 509.53, "py": 276.25}, {"player": "a0738c7c-612e-45c9-b24d-057115642057", "is_human": true, "type": "Position", "ts": 1770770366, "px": 505.07, "py": 278.58}, {"player": "a0738c7c-612e-45c9-b24d-057115642057", "is_human": true, "type": "Position", "ts": 1770770371, "px": 499.04, "py": 282.51}, {"player": "a0738c7c-612e-45c9-b24d-057115642057", "is_human": true, "type": "Position", "ts": 1770770376, "px": 500.66, "py": 278.98}, {"player": "a0738c7c-612e-45c9-b24d-057115642057", "is_human": true, "type": "Position", "ts": 1770770381, "px": 511.59, "py": 273.45}, {"player": "a0738c7c-612e-45c9-b24d-057115642057", "is_human": true, "type": "Position", "ts": 1770770386, "px": 530.09, "py": 268.58}, {"player": "a0738c7c-612e-45c9-b24d-057115642057", "is_human": true, "type": "Position", "ts": 1770770391, "px": 536.0, "py": 278.39}, {"player": "a0738c7c-612e-45c9-b24d-057115642057", "is_human": true, "type": "Position", "ts": 1770770396, "px": 539.12, "py": 277.71}, {"player": "a0738c7c-612e-45c9-b24d-057115642057", "is_human": true, "type": "Position", "ts": 1770770401, "px": 555.07, "py": 267.03}, {"player": "a0738c7c-612e-45c9-b24d-057115642057", "is_human": true, "type": "Position", "ts": 1770770406, "px": 559.72, "py": 266.86}, {"player": "a0738c7c-612e-45c9-b24d-057115642057", "is_human": true, "type": "Position", "ts": 1770770416, "px": 564.55, "py": 264.03}, {"player": "a0738c7c-612e-45c9-b24d-057115642057", "is_human": true, "type": "Position", "ts": 1770770431, "px": 561.85, "py": 262.99}, {"player": "a0738c7c-612e-45c9-b24d-057115642057", "is_human": true, "type": "Position", "ts": 1770770436, "px": 566.75, "py": 264.24}, {"player": "a0738c7c-612e-45c9-b24d-057115642057", "is_human": true, "type": "Position", "ts": 1770770466, "px": 561.43, "py": 261.71}, {"player": "a0738c7c-612e-45c9-b24d-057115642057", "is_human": true, "type": "BotKill", "ts": 1770770470, "px": 559.08, "py": 262.14}, {"player": "a0738c7c-612e-45c9-b24d-057115642057", "is_human": true, "type": "Position", "ts": 1770770477, "px": 577.53, "py": 263.84}, {"player": "a0738c7c-612e-45c9-b24d-057115642057", "is_human": true, "type": "Position", "ts": 1770770482, "px": 602.62, "py": 272.28}, {"player": "a0738c7c-612e-45c9-b24d-057115642057", "is_human": true, "type": "Position", "ts": 1770770487, "px": 611.45, "py": 265.89}, {"player": "a0738c7c-612e-45c9-b24d-057115642057", "is_human": true, "type": "Loot", "ts": 1770770490, "px": 609.87, "py": 266.55}, {"player": "a0738c7c-612e-45c9-b24d-057115642057", "is_human": true, "type": "Position", "ts": 1770770492, "px": 613.6, "py": 269.19}, {"player": "a0738c7c-612e-45c9-b24d-057115642057", "is_human": true, "type": "Position", "ts": 1770770497, "px": 642.23, "py": 273.78}, {"player": "a0738c7c-612e-45c9-b24d-057115642057", "is_human": true, "type": "Position", "ts": 1770770502, "px": 652.25, "py": 293.68}, {"player": "a0738c7c-612e-45c9-b24d-057115642057", "is_human": true, "type": "Position", "ts": 1770770507, "px": 646.39, "py": 307.49}, {"player": "a0738c7c-612e-45c9-b24d-057115642057", "is_human": true, "type": "Position", "ts": 1770770512, "px": 652.93, "py": 334.22}, {"player": "a0738c7c-612e-45c9-b24d-057115642057", "is_human": true, "type": "Position", "ts": 1770770517, "px": 679.13, "py": 345.95}, {"player": "a0738c7c-612e-45c9-b24d-057115642057", "is_human": true, "type": "Position", "ts": 1770770522, "px": 699.97, "py": 367.27}, {"player": "a0738c7c-612e-45c9-b24d-057115642057", "is_human": true, "type": "Position", "ts": 1770770527, "px": 713.09, "py": 380.38}, {"player": "a0738c7c-612e-45c9-b24d-057115642057", "is_human": true, "type": "Position", "ts": 1770770532, "px": 738.01, "py": 389.03}, {"player": "a0738c7c-612e-45c9-b24d-057115642057", "is_human": true, "type": "Position", "ts": 1770770537, "px": 767.54, "py": 393.94}, {"player": "a0738c7c-612e-45c9-b24d-057115642057", "is_human": true, "type": "Position", "ts": 1770770542, "px": 787.43, "py": 397.25}, {"player": "a0738c7c-612e-45c9-b24d-057115642057", "is_human": true, "type": "KilledByStorm", "ts": 1770770544, "px": 800.35, "py": 399.54}, {"player": "a0738c7c-612e-45c9-b24d-057115642057", "is_human": true, "type": "Position", "ts": 1770770547, "px": 800.46, "py": 399.87}], "humans_count": 1, "bots_count": 0, "events_count": 167}