{"match_id": "21fd8c9f-c619-405f-849c-77c5529b1eb9.nakama-0", "map_id": "AmbroseValley", "date": "February 13", "events": [{"player": "2898ee70-495f-42a2-8c5a-ffc4ed813fad", "is_human": true, "type": "Position", "ts": 1770963015, "px": 77.41, "py": 885.01}, {"player": "2898ee70-495f-42a2-8c5a-ffc4ed813fad", "is_human": true, "type": "Position", "ts": 1770963030, "px": 99.36, "py": 878.78}, {"player": "2898ee70-495f-42a2-8c5a-ffc4ed813fad", "is_human": true, "type": "Position", "ts": 1770963035, "px": 135.1, "py": 871.5}, {"player": "2898ee70-495f-42a2-8c5a-ffc4ed813fad", "is_human": true, "type": "Loot", "ts": 1770963040, "px": 163.34, "py": 859.67}, {"player": "2898ee70-495f-42a2-8c5a-ffc4ed813fad", "is_human": true, "type": "Position", "ts": 1770963040, "px": 163.34, "py": 859.67}, {"player": "2898ee70-495f-42a2-8c5a-ffc4ed813fad", "is_human": true, "type": "Position", "ts": 1770963045, "px": 179.3, "py": 852.41}, {"player": "2898ee70-495f-42a2-8c5a-ffc4ed813fad", "is_human": true, "type": "Position", "ts": 1770963050, "px": 170.49, "py": 861.29}, {"player": "2898ee70-495f-42a2-8c5a-ffc4ed813fad", "is_human": true, "type": "Position", "ts": 1770963055, "px": 161.26, "py": 870.99}, {"player": "2898ee70-495f-42a2-8c5a-ffc4ed813fad", "is_human": true, "type": "Loot", "ts": 1770963055, "px": 161.26, "py": 870.99}, {"player": "2898ee70-495f-42a2-8c5a-ffc4ed813fad", "is_human": true, "type": "Loot", "ts": 1770963056, "px": 161.26, "py": 870.99}, {"player": "2898ee70-495f-42a2-8c5a-ffc4ed813fad", "is_human": true, "type": "Position", "ts": 1770963060, "px": 186.43, "py": 859.85}, {"player": "2898ee70-495f-42a2-8c5a-ffc4ed813fad", "is_human": true, "type": "Position", "ts": 1770963065, "px": 217.76, "py": 846.85}, {"player": "2898ee70-495f-42a2-8c5a-ffc4ed813fad", "is_human": true, "type": "Position", "ts": 1770963070, "px": 213.2, "py": 856.26}, {"player": "2898ee70-495f-42a2-8c5a-ffc4ed813fad", "is_human": true, "type": "Position", "ts": 1770963076, "px": 214.42, "py": 852.89}, {"player": "2898ee70-495f-42a2-8c5a-ffc4ed813fad", "is_human": true, "type": "BotKill", "ts": 1770963080, "px": 210.46, "py": 856.58}, {"player": "2898ee70-495f-42a2-8c5a-ffc4ed813fad", "is_human": true, "type": "Position", "ts": 1770963081, "px": 210.58, "py": 856.52}, {"player": "2898ee70-495f-42a2-8c5a-ffc4ed813fad", "is_human": true, "type": "Loot", "ts": 1770963082, "px": 212.68, "py": 855.57}, {"player": "2898ee70-495f-42a2-8c5a-ffc4ed813fad", "is_human": true, "type": "Loot", "ts": 1770963082, "px": 212.68, "py": 855.57}, {"player": "2898ee70-495f-42a2-8c5a-ffc4ed813fad", "is_human": true, "type": "Position", "ts": 1770963086, "px": 211.63, "py": 854.1}, {"player": "2898ee70-495f-42a2-8c5a-ffc4ed813fad", "is_human": true, "type": "Position", "ts": 1770963091, "px": 226.8, "py": 854.89}, {"player": "2898ee70-495f-42a2-8c5a-ffc4ed813fad", "is_human": true, "type": "Position", "ts": 1770963096, "px": 233.66, "py": 856.39}, {"player": "2898ee70-495f-42a2-8c5a-ffc4ed813fad", "is_human": true, "type": "Position", "ts": 1770963101, "px": 223.99, "py": 836.25}, {"player": "2898ee70-495f-42a2-8c5a-ffc4ed813fad", "is_human": true, "type": "Position", "ts": 1770963106, "px": 235.18, "py": 806.89}, {"player": "2898ee70-495f-42a2-8c5a-ffc4ed813fad", "is_human": true, "type": "Position", "ts": 1770963111, "px": 244.18, "py": 771.96}, {"player": "2898ee70-495f-42a2-8c5a-ffc4ed813fad", "is_human": true, "type": "Position", "ts": 1770963116, "px": 252.35, "py": 739.48}, {"player": "2898ee70-495f-42a2-8c5a-ffc4ed813fad", "is_human": true, "type": "Position", "ts": 1770963121, "px": 257.41, "py": 714.39}, {"player": "2898ee70-495f-42a2-8c5a-ffc4ed813fad", "is_human": true, "type": "Position", "ts": 1770963126, "px": 259.57, "py": 681.79}, {"player": "2898ee70-495f-42a2-8c5a-ffc4ed813fad", "is_human": true, "type": "Position", "ts": 1770963131, "px": 284.95, "py": 665.3}, {"player": "2898ee70-495f-42a2-8c5a-ffc4ed813fad", "is_human": true, "type": "Position", "ts": 1770963136, "px": 311.1, "py": 656.89}, {"player": "2898ee70-495f-42a2-8c5a-ffc4ed813fad", "is_human": true, "type": "Position", "ts": 1770963141, "px": 319.99, "py": 652.33}, {"player": "2898ee70-495f-42a2-8c5a-ffc4ed813fad", "is_human": true, "type": "Position", "ts": 1770963146, "px": 339.36, "py": 647.18}, {"player": "2898ee70-495f-42a2-8c5a-ffc4ed813fad", "is_human": true, "type": "Position", "ts": 1770963151, "px": 343.63, "py": 613.44}, {"player": "2898ee70-495f-42a2-8c5a-ffc4ed813fad", "is_human": true, "type": "Position", "ts": 1770963156, "px": 343.14, "py": 581.88}, {"player": "2898ee70-495f-42a2-8c5a-ffc4ed813fad", "is_human": true, "type": "BotKill", "ts": 1770963158, "px": 343.46, "py": 581.24}, {"player": "2898ee70-495f-42a2-8c5a-ffc4ed813fad", "is_human": true, "type": "Position", "ts": 1770963161, "px": 340.06, "py": 577.83}, {"player": "2898ee70-495f-42a2-8c5a-ffc4ed813fad", "is_human": true, "type": "BotKill", "ts": 1770963162, "px": 342.01, "py": 578.46}, {"player": "2898ee70-495f-42a2-8c5a-ffc4ed813fad", "is_human": true, "type": "BotKill", "ts": 1770963166, "px": 339.63, "py": 574.04}, {"player": "2898ee70-495f-42a2-8c5a-ffc4ed813fad", "is_human": true, "type": "Position", "ts": 1770963166, "px": 339.81, "py": 575.25}, {"player": "2898ee70-495f-42a2-8c5a-ffc4ed813fad", "is_human": true, "type": "Loot", "ts": 1770963168, "px": 343.44, "py": 578.5}, {"player": "2898ee70-495f-42a2-8c5a-ffc4ed813fad", "is_human": true, "type": "Loot", "ts": 1770963168, "px": 344.72, "py": 578.97}, {"player": "2898ee70-495f-42a2-8c5a-ffc4ed813fad", "is_human": true, "type": "Loot", "ts": 1770963170, "px": 353.92, "py": 581.96}, {"player": "2898ee70-495f-42a2-8c5a-ffc4ed813fad", "is_human": true, "type": "Loot", "ts": 1770963170, "px": 353.89, "py": 582.58}, {"player": "2898ee70-495f-42a2-8c5a-ffc4ed813fad", "is_human": true, "type": "Position", "ts": 1770963171, "px": 357.12, "py": 581.5}, {"player": "2898ee70-495f-42a2-8c5a-ffc4ed813fad", "is_human": true, "type": "Position", "ts": 1770963176, "px": 351.86, "py": 567.84}, {"player": "2898ee70-495f-42a2-8c5a-ffc4ed813fad", "is_human": true, "type": "Position", "ts": 1770963181, "px": 329.16, "py": 569.32}, {"player": "2898ee70-495f-42a2-8c5a-ffc4ed813fad", "is_human": true, "type": "Position", "ts": 1770963186, "px": 312.16, "py": 550.88}, {"player": "2898ee70-495f-42a2-8c5a-ffc4ed813fad", "is_human": true, "type": "Position", "ts": 1770963191, "px": 301.71, "py": 539.77}, {"player": "2898ee70-495f-42a2-8c5a-ffc4ed813fad", "is_human": true, "type": "Position", "ts": 1770963196, "px": 286.63, "py": 518.68}], "humans_count": 1, "bots_count": 0, "events_count": 48}