{"match_id": "22d06fe8-441b-48b4-b245-493696e5515f.nakama-0", "map_id": "GrandRift", "date": "February 11", "events": [{"player": "fbf6abaf-0686-4f96-8cda-77071d195268", "is_human": true, "type": "Position", "ts": 1770833590, "px": 796.61, "py": 243.26}, {"player": "fbf6abaf-0686-4f96-8cda-77071d195268", "is_human": true, "type": "Position", "ts": 1770833600, "px": 772.67, "py": 273.5}, {"player": "fbf6abaf-0686-4f96-8cda-77071d195268", "is_human": true, "type": "Position", "ts": 1770833605, "px": 774.45, "py": 284.21}, {"player": "fbf6abaf-0686-4f96-8cda-77071d195268", "is_human": true, "type": "Position", "ts": 1770833610, "px": 773.38, "py": 305.86}, {"player": "fbf6abaf-0686-4f96-8cda-77071d195268", "is_human": true, "type": "Position", "ts": 1770833615, "px": 766.72, "py": 314.02}, {"player": "fbf6abaf-0686-4f96-8cda-77071d195268", "is_human": true, "type": "Position", "ts": 1770833621, "px": 762.74, "py": 304.02}, {"player": "fbf6abaf-0686-4f96-8cda-77071d195268", "is_human": true, "type": "Position", "ts": 1770833626, "px": 744.43, "py": 304.93}, {"player": "fbf6abaf-0686-4f96-8cda-77071d195268", "is_human": true, "type": "Position", "ts": 1770833631, "px": 721.89, "py": 289.04}, {"player": "fbf6abaf-0686-4f96-8cda-77071d195268", "is_human": true, "type": "Position", "ts": 1770833636, "px": 673.84, "py": 266.07}, {"player": "fbf6abaf-0686-4f96-8cda-77071d195268", "is_human": true, "type": "Position", "ts": 1770833641, "px": 655.25, "py": 259.83}, {"player": "fbf6abaf-0686-4f96-8cda-77071d195268", "is_human": true, "type": "Loot", "ts": 1770833641, "px": 655.25, "py": 259.83}, {"player": "fbf6abaf-0686-4f96-8cda-77071d195268", "is_human": true, "type": "Position", "ts": 1770833646, "px": 667.49, "py": 271.61}, {"player": "fbf6abaf-0686-4f96-8cda-77071d195268", "is_human": true, "type": "Loot", "ts": 1770833650, "px": 670.66, "py": 287.11}, {"player": "fbf6abaf-0686-4f96-8cda-77071d195268", "is_human": true, "type": "Position", "ts": 1770833651, "px": 670.66, "py": 287.11}, {"player": "fbf6abaf-0686-4f96-8cda-77071d195268", "is_human": true, "type": "Position", "ts": 1770833656, "px": 691.26, "py": 285.33}, {"player": "fbf6abaf-0686-4f96-8cda-77071d195268", "is_human": true, "type": "Position", "ts": 1770833661, "px": 699.84, "py": 306.59}, {"player": "fbf6abaf-0686-4f96-8cda-77071d195268", "is_human": true, "type": "Position", "ts": 1770833666, "px": 713.34, "py": 357.64}, {"player": "fbf6abaf-0686-4f96-8cda-77071d195268", "is_human": true, "type": "Position", "ts": 1770833671, "px": 728.3, "py": 409.01}, {"player": "fbf6abaf-0686-4f96-8cda-77071d195268", "is_human": true, "type": "Position", "ts": 1770833676, "px": 693.15, "py": 449.11}, {"player": "fbf6abaf-0686-4f96-8cda-77071d195268", "is_human": true, "type": "Loot", "ts": 1770833680, "px": 689.36, "py": 453.83}, {"player": "fbf6abaf-0686-4f96-8cda-77071d195268", "is_human": true, "type": "Position", "ts": 1770833681, "px": 689.36, "py": 453.83}, {"player": "fbf6abaf-0686-4f96-8cda-77071d195268", "is_human": true, "type": "Position", "ts": 1770833686, "px": 693.24, "py": 485.31}, {"player": "fbf6abaf-0686-4f96-8cda-77071d195268", "is_human": true, "type": "Loot", "ts": 1770833691, "px": 689.46, "py": 501.81}, {"player": "fbf6abaf-0686-4f96-8cda-77071d195268", "is_human": true, "type": "Position", "ts": 1770833691, "px": 689.46, "py": 501.81}, {"player": "fbf6abaf-0686-4f96-8cda-77071d195268", "is_human": true, "type": "Position", "ts": 1770833696, "px": 673.36, "py": 510.9}, {"player": "fbf6abaf-0686-4f96-8cda-77071d195268", "is_human": true, "type": "Position", "ts": 1770833711, "px": 690.81, "py": 506.38}, {"player": "fbf6abaf-0686-4f96-8cda-77071d195268", "is_human": true, "type": "Position", "ts": 1770833716, "px": 680.6, "py": 493.73}, {"player": "fbf6abaf-0686-4f96-8cda-77071d195268", "is_human": true, "type": "BotKill", "ts": 1770833720, "px": 682.1, "py": 494.68}, {"player": "fbf6abaf-0686-4f96-8cda-77071d195268", "is_human": true, "type": "Loot", "ts": 1770833724, "px": 689.81, "py": 500.43}, {"player": "fbf6abaf-0686-4f96-8cda-77071d195268", "is_human": true, "type": "Loot", "ts": 1770833724, "px": 689.81, "py": 500.43}, {"player": "fbf6abaf-0686-4f96-8cda-77071d195268", "is_human": true, "type": "Loot", "ts": 1770833724, "px": 689.81, "py": 500.43}, {"player": "fbf6abaf-0686-4f96-8cda-77071d195268", "is_human": true, "type": "Loot", "ts": 1770833724, "px": 689.81, "py": 500.43}, {"player": "fbf6abaf-0686-4f96-8cda-77071d195268", "is_human": true, "type": "Loot", "ts": 1770833724, "px": 689.81, "py": 500.43}, {"player": "fbf6abaf-0686-4f96-8cda-77071d195268", "is_human": true, "type": "Loot", "ts": 1770833724, "px": 689.81, "py": 500.43}, {"player": "fbf6abaf-0686-4f96-8cda-77071d195268", "is_human": true, "type": "Loot", "ts": 1770833724, "px": 689.81, "py": 500.43}, {"player": "fbf6abaf-0686-4f96-8cda-77071d195268", "is_human": true, "type": "Position", "ts": 1770833726, "px": 692.58, "py": 501.5}, {"player": "fbf6abaf-0686-4f96-8cda-77071d195268", "is_human": true, "type": "Position", "ts": 1770833731, "px": 703.7, "py": 495.17}, {"player": "fbf6abaf-0686-4f96-8cda-77071d195268", "is_human": true, "type": "Position", "ts": 1770833736, "px": 715.72, "py": 490.08}, {"player": "fbf6abaf-0686-4f96-8cda-77071d195268", "is_human": true, "type": "Position", "ts": 1770833741, "px": 722.7, "py": 495.38}, {"player": "fbf6abaf-0686-4f96-8cda-77071d195268", "is_human": true, "type": "BotKill", "ts": 1770833744, "px": 739.34, "py": 497.91}, {"player": "fbf6abaf-0686-4f96-8cda-77071d195268", "is_human": true, "type": "Position", "ts": 1770833746, "px": 749.12, "py": 502.2}, {"player": "fbf6abaf-0686-4f96-8cda-77071d195268", "is_human": true, "type": "Loot", "ts": 1770833747, "px": 749.12, "py": 502.2}, {"player": "fbf6abaf-0686-4f96-8cda-77071d195268", "is_human": true, "type": "Loot", "ts": 1770833747, "px": 749.12, "py": 502.2}, {"player": "fbf6abaf-0686-4f96-8cda-77071d195268", "is_human": true, "type": "Position", "ts": 1770833751, "px": 757.9, "py": 502.04}, {"player": "fbf6abaf-0686-4f96-8cda-77071d195268", "is_human": true, "type": "Position", "ts": 1770833756, "px": 779.39, "py": 513.58}, {"player": "fbf6abaf-0686-4f96-8cda-77071d195268", "is_human": true, "type": "Position", "ts": 1770833761, "px": 801.01, "py": 506.09}, {"player": "fbf6abaf-0686-4f96-8cda-77071d195268", "is_human": true, "type": "BotKill", "ts": 1770833766, "px": 814.29, "py": 509.07}, {"player": "fbf6abaf-0686-4f96-8cda-77071d195268", "is_human": true, "type": "Position", "ts": 1770833766, "px": 816.18, "py": 509.56}, {"player": "fbf6abaf-0686-4f96-8cda-77071d195268", "is_human": true, "type": "BotKill", "ts": 1770833767, "px": 819.28, "py": 510.41}, {"player": "fbf6abaf-0686-4f96-8cda-77071d195268", "is_human": true, "type": "BotKill", "ts": 1770833768, "px": 821.83, "py": 511.98}, {"player": "fbf6abaf-0686-4f96-8cda-77071d195268", "is_human": true, "type": "Loot", "ts": 1770833768, "px": 821.83, "py": 511.98}, {"player": "fbf6abaf-0686-4f96-8cda-77071d195268", "is_human": true, "type": "Loot", "ts": 1770833768, "px": 821.83, "py": 511.98}, {"player": "fbf6abaf-0686-4f96-8cda-77071d195268", "is_human": true, "type": "Position", "ts": 1770833771, "px": 831.31, "py": 526.73}, {"player": "fbf6abaf-0686-4f96-8cda-77071d195268", "is_human": true, "type": "Position", "ts": 1770833776, "px": 835.36, "py": 538.34}, {"player": "fbf6abaf-0686-4f96-8cda-77071d195268", "is_human": true, "type": "Position", "ts": 1770833781, "px": 826.35, "py": 520.73}, {"player": "fbf6abaf-0686-4f96-8cda-77071d195268", "is_human": true, "type": "Position", "ts": 1770833786, "px": 798.74, "py": 512.15}, {"player": "fbf6abaf-0686-4f96-8cda-77071d195268", "is_human": true, "type": "Loot", "ts": 1770833789, "px": 790.05, "py": 516.63}, {"player": "fbf6abaf-0686-4f96-8cda-77071d195268", "is_human": true, "type": "Position", "ts": 1770833791, "px": 798.03, "py": 531.91}, {"player": "fbf6abaf-0686-4f96-8cda-77071d195268", "is_human": true, "type": "Position", "ts": 1770833796, "px": 812.13, "py": 532.39}, {"player": "fbf6abaf-0686-4f96-8cda-77071d195268", "is_human": true, "type": "Position", "ts": 1770833802, "px": 821.36, "py": 551.13}, {"player": "fbf6abaf-0686-4f96-8cda-77071d195268", "is_human": true, "type": "Position", "ts": 1770833807, "px": 835.92, "py": 550.57}, {"player": "fbf6abaf-0686-4f96-8cda-77071d195268", "is_human": true, "type": "Loot", "ts": 1770833807, "px": 835.92, "py": 550.57}, {"player": "fbf6abaf-0686-4f96-8cda-77071d195268", "is_human": true, "type": "Position", "ts": 1770833812, "px": 848.84, "py": 544.12}, {"player": "fbf6abaf-0686-4f96-8cda-77071d195268", "is_human": true, "type": "Position", "ts": 1770833817, "px": 851.72, "py": 576.72}, {"player": "fbf6abaf-0686-4f96-8cda-77071d195268", "is_human": true, "type": "Position", "ts": 1770833822, "px": 815.81, "py": 587.47}, {"player": "fbf6abaf-0686-4f96-8cda-77071d195268", "is_human": true, "type": "Position", "ts": 1770833827, "px": 776.82, "py": 553.5}, {"player": "fbf6abaf-0686-4f96-8cda-77071d195268", "is_human": true, "type": "Position", "ts": 1770833832, "px": 738.28, "py": 524.47}, {"player": "fbf6abaf-0686-4f96-8cda-77071d195268", "is_human": true, "type": "Position", "ts": 1770833837, "px": 719.86, "py": 522.27}, {"player": "fbf6abaf-0686-4f96-8cda-77071d195268", "is_human": true, "type": "Position", "ts": 1770833842, "px": 727.74, "py": 527.37}, {"player": "fbf6abaf-0686-4f96-8cda-77071d195268", "is_human": true, "type": "Position", "ts": 1770833847, "px": 728.67, "py": 532.08}, {"player": "fbf6abaf-0686-4f96-8cda-77071d195268", "is_human": true, "type": "BotKill", "ts": 1770833848, "px": 729.58, "py": 529.13}, {"player": "fbf6abaf-0686-4f96-8cda-77071d195268", "is_human": true, "type": "BotKill", "ts": 1770833853, "px": 728.83, "py": 531.71}, {"player": "fbf6abaf-0686-4f96-8cda-77071d195268", "is_human": true, "type": "Position", "ts": 1770833857, "px": 729.42, "py": 530.5}, {"player": "fbf6abaf-0686-4f96-8cda-77071d195268", "is_human": true, "type": "Loot", "ts": 1770833863, "px": 729.73, "py": 528.07}, {"player": "fbf6abaf-0686-4f96-8cda-77071d195268", "is_human": true, "type": "Loot", "ts": 1770833863, "px": 729.73, "py": 528.07}, {"player": "fbf6abaf-0686-4f96-8cda-77071d195268", "is_human": true, "type": "Position", "ts": 1770833872, "px": 702.85, "py": 504.01}, {"player": "fbf6abaf-0686-4f96-8cda-77071d195268", "is_human": true, "type": "Position", "ts": 1770833877, "px": 693.06, "py": 499.24}, {"player": "fbf6abaf-0686-4f96-8cda-77071d195268", "is_human": true, "type": "BotKill", "ts": 1770833880, "px": 689.88, "py": 499.11}, {"player": "fbf6abaf-0686-4f96-8cda-77071d195268", "is_human": true, "type": "Position", "ts": 1770833882, "px": 687.11, "py": 498.6}, {"player": "fbf6abaf-0686-4f96-8cda-77071d195268", "is_human": true, "type": "Loot", "ts": 1770833886, "px": 684.05, "py": 499.83}, {"player": "fbf6abaf-0686-4f96-8cda-77071d195268", "is_human": true, "type": "Loot", "ts": 1770833886, "px": 684.05, "py": 499.83}, {"player": "fbf6abaf-0686-4f96-8cda-77071d195268", "is_human": true, "type": "Position", "ts": 1770833892, "px": 655.86, "py": 516.92}, {"player": "fbf6abaf-0686-4f96-8cda-77071d195268", "is_human": true, "type": "Position", "ts": 1770833897, "px": 617.13, "py": 501.84}, {"player": "fbf6abaf-0686-4f96-8cda-77071d195268", "is_human": true, "type": "Position", "ts": 1770833902, "px": 586.91, "py": 461.89}, {"player": "fbf6abaf-0686-4f96-8cda-77071d195268", "is_human": true, "type": "Position", "ts": 1770833907, "px": 556.01, "py": 420.66}, {"player": "fbf6abaf-0686-4f96-8cda-77071d195268", "is_human": true, "type": "Position", "ts": 1770833912, "px": 540.07, "py": 403.4}, {"player": "fbf6abaf-0686-4f96-8cda-77071d195268", "is_human": true, "type": "Position", "ts": 1770833917, "px": 527.09, "py": 384.57}, {"player": "fbf6abaf-0686-4f96-8cda-77071d195268", "is_human": true, "type": "Position", "ts": 1770833922, "px": 524.56, "py": 360.57}, {"player": "fbf6abaf-0686-4f96-8cda-77071d195268", "is_human": true, "type": "Position", "ts": 1770833927, "px": 496.86, "py": 332.05}, {"player": "fbf6abaf-0686-4f96-8cda-77071d195268", "is_human": true, "type": "Position", "ts": 1770833932, "px": 473.87, "py": 314.36}, {"player": "fbf6abaf-0686-4f96-8cda-77071d195268", "is_human": true, "type": "Position", "ts": 1770833937, "px": 467.32, "py": 304.09}, {"player": "fbf6abaf-0686-4f96-8cda-77071d195268", "is_human": true, "type": "Position", "ts": 1770833942, "px": 471.82, "py": 279.87}, {"player": "fbf6abaf-0686-4f96-8cda-77071d195268", "is_human": true, "type": "Position", "ts": 1770833952, "px": 472.52, "py": 274.48}, {"player": "fbf6abaf-0686-4f96-8cda-77071d195268", "is_human": true, "type": "Position", "ts": 1770833957, "px": 471.74, "py": 277.97}, {"player": "fbf6abaf-0686-4f96-8cda-77071d195268", "is_human": true, "type": "Position", "ts": 1770833998, "px": 492.76, "py": 257.86}, {"player": "fbf6abaf-0686-4f96-8cda-77071d195268", "is_human": true, "type": "Position", "ts": 1770834003, "px": 493.85, "py": 260.53}, {"player": "fbf6abaf-0686-4f96-8cda-77071d195268", "is_human": true, "type": "Position", "ts": 1770834013, "px": 493.13, "py": 258.38}, {"player": "fbf6abaf-0686-4f96-8cda-77071d195268", "is_human": true, "type": "Position", "ts": 1770834078, "px": 475.89, "py": 265.34}, {"player": "fbf6abaf-0686-4f96-8cda-77071d195268", "is_human": true, "type": "Position", "ts": 1770834083, "px": 466.72, "py": 240.99}, {"player": "fbf6abaf-0686-4f96-8cda-77071d195268", "is_human": true, "type": "Position", "ts": 1770834088, "px": 457.53, "py": 248.51}, {"player": "fbf6abaf-0686-4f96-8cda-77071d195268", "is_human": true, "type": "Position", "ts": 1770834098, "px": 458.77, "py": 249.75}, {"player": "fbf6abaf-0686-4f96-8cda-77071d195268", "is_human": true, "type": "Position", "ts": 1770834108, "px": 455.93, "py": 256.07}, {"player": "fbf6abaf-0686-4f96-8cda-77071d195268", "is_human": true, "type": "Position", "ts": 1770834118, "px": 452.98, "py": 261.95}, {"player": "fbf6abaf-0686-4f96-8cda-77071d195268", "is_human": true, "type": "Position", "ts": 1770834123, "px": 447.31, "py": 266.18}, {"player": "fbf6abaf-0686-4f96-8cda-77071d195268", "is_human": true, "type": "Position", "ts": 1770834128, "px": 439.98, "py": 266.03}, {"player": "fbf6abaf-0686-4f96-8cda-77071d195268", "is_human": true, "type": "Position", "ts": 1770834133, "px": 432.79, "py": 267.92}, {"player": "fbf6abaf-0686-4f96-8cda-77071d195268", "is_human": true, "type": "BotKilled", "ts": 1770834135, "px": 431.11, "py": 267.27}, {"player": "fbf6abaf-0686-4f96-8cda-77071d195268", "is_human": true, "type": "Position", "ts": 1770834138, "px": 431.11, "py": 267.27}], "humans_count": 1, "bots_count": 0, "events_count": 108}