{"match_id": "320bf45f-a6d5-4bf4-9f68-c9b051b7a9ba.nakama-0", "map_id": "AmbroseValley", "date": "February 10", "events": [{"player": "409f0ae7-a4cf-4005-9c04-1f8fb2059a12", "is_human": true, "type": "Position", "ts": 1770738044, "px": 64.59, "py": 484.52}, {"player": "409f0ae7-a4cf-4005-9c04-1f8fb2059a12", "is_human": true, "type": "Position", "ts": 1770738064, "px": 65.67, "py": 466.33}, {"player": "409f0ae7-a4cf-4005-9c04-1f8fb2059a12", "is_human": true, "type": "Position", "ts": 1770738069, "px": 85.59, "py": 447.63}, {"player": "409f0ae7-a4cf-4005-9c04-1f8fb2059a12", "is_human": true, "type": "Position", "ts": 1770738074, "px": 97.25, "py": 425.9}, {"player": "409f0ae7-a4cf-4005-9c04-1f8fb2059a12", "is_human": true, "type": "Position", "ts": 1770738079, "px": 100.88, "py": 417.94}, {"player": "409f0ae7-a4cf-4005-9c04-1f8fb2059a12", "is_human": true, "type": "Loot", "ts": 1770738082, "px": 101.4, "py": 417.57}, {"player": "409f0ae7-a4cf-4005-9c04-1f8fb2059a12", "is_human": true, "type": "Position", "ts": 1770738084, "px": 100.02, "py": 417.1}, {"player": "409f0ae7-a4cf-4005-9c04-1f8fb2059a12", "is_human": true, "type": "Position", "ts": 1770738089, "px": 96.02, "py": 416.13}, {"player": "409f0ae7-a4cf-4005-9c04-1f8fb2059a12", "is_human": true, "type": "Loot", "ts": 1770738094, "px": 87.54, "py": 417.93}, {"player": "409f0ae7-a4cf-4005-9c04-1f8fb2059a12", "is_human": true, "type": "Position", "ts": 1770738094, "px": 87.54, "py": 417.93}, {"player": "409f0ae7-a4cf-4005-9c04-1f8fb2059a12", "is_human": true, "type": "Loot", "ts": 1770738096, "px": 87.96, "py": 414.25}, {"player": "409f0ae7-a4cf-4005-9c04-1f8fb2059a12", "is_human": true, "type": "Position", "ts": 1770738099, "px": 94.37, "py": 410.1}, {"player": "409f0ae7-a4cf-4005-9c04-1f8fb2059a12", "is_human": true, "type": "Position", "ts": 1770738104, "px": 101.22, "py": 407.59}, {"player": "409f0ae7-a4cf-4005-9c04-1f8fb2059a12", "is_human": true, "type": "Loot", "ts": 1770738107, "px": 105.8, "py": 405.67}, {"player": "409f0ae7-a4cf-4005-9c04-1f8fb2059a12", "is_human": true, "type": "Position", "ts": 1770738110, "px": 103.83, "py": 403.25}, {"player": "409f0ae7-a4cf-4005-9c04-1f8fb2059a12", "is_human": true, "type": "Position", "ts": 1770738115, "px": 102.72, "py": 399.66}, {"player": "409f0ae7-a4cf-4005-9c04-1f8fb2059a12", "is_human": true, "type": "Position", "ts": 1770738120, "px": 94.86, "py": 411.21}, {"player": "409f0ae7-a4cf-4005-9c04-1f8fb2059a12", "is_human": true, "type": "Position", "ts": 1770738125, "px": 85.42, "py": 409.31}, {"player": "409f0ae7-a4cf-4005-9c04-1f8fb2059a12", "is_human": true, "type": "Position", "ts": 1770738130, "px": 94.72, "py": 399.87}, {"player": "409f0ae7-a4cf-4005-9c04-1f8fb2059a12", "is_human": true, "type": "Loot", "ts": 1770738130, "px": 94.72, "py": 399.87}, {"player": "409f0ae7-a4cf-4005-9c04-1f8fb2059a12", "is_human": true, "type": "Loot", "ts": 1770738131, "px": 94.72, "py": 399.87}, {"player": "409f0ae7-a4cf-4005-9c04-1f8fb2059a12", "is_human": true, "type": "Position", "ts": 1770738135, "px": 107.98, "py": 390.8}, {"player": "409f0ae7-a4cf-4005-9c04-1f8fb2059a12", "is_human": true, "type": "Position", "ts": 1770738140, "px": 125.56, "py": 417.28}, {"player": "409f0ae7-a4cf-4005-9c04-1f8fb2059a12", "is_human": true, "type": "Position", "ts": 1770738145, "px": 147.16, "py": 398.9}, {"player": "409f0ae7-a4cf-4005-9c04-1f8fb2059a12", "is_human": true, "type": "Loot", "ts": 1770738146, "px": 149.27, "py": 396.41}, {"player": "409f0ae7-a4cf-4005-9c04-1f8fb2059a12", "is_human": true, "type": "Position", "ts": 1770738150, "px": 149.27, "py": 396.41}, {"player": "409f0ae7-a4cf-4005-9c04-1f8fb2059a12", "is_human": true, "type": "Position", "ts": 1770738155, "px": 146.22, "py": 412.53}, {"player": "409f0ae7-a4cf-4005-9c04-1f8fb2059a12", "is_human": true, "type": "Position", "ts": 1770738160, "px": 161.74, "py": 405.15}, {"player": "409f0ae7-a4cf-4005-9c04-1f8fb2059a12", "is_human": true, "type": "Position", "ts": 1770738165, "px": 183.93, "py": 408.27}, {"player": "409f0ae7-a4cf-4005-9c04-1f8fb2059a12", "is_human": true, "type": "Position", "ts": 1770738170, "px": 206.6, "py": 417.23}, {"player": "409f0ae7-a4cf-4005-9c04-1f8fb2059a12", "is_human": true, "type": "Position", "ts": 1770738175, "px": 227.85, "py": 418.22}, {"player": "409f0ae7-a4cf-4005-9c04-1f8fb2059a12", "is_human": true, "type": "Position", "ts": 1770738180, "px": 217.19, "py": 409.49}, {"player": "409f0ae7-a4cf-4005-9c04-1f8fb2059a12", "is_human": true, "type": "Position", "ts": 1770738185, "px": 225.57, "py": 395.04}, {"player": "409f0ae7-a4cf-4005-9c04-1f8fb2059a12", "is_human": true, "type": "Position", "ts": 1770738190, "px": 219.82, "py": 381.75}, {"player": "409f0ae7-a4cf-4005-9c04-1f8fb2059a12", "is_human": true, "type": "BotKill", "ts": 1770738194, "px": 217.02, "py": 373.75}, {"player": "409f0ae7-a4cf-4005-9c04-1f8fb2059a12", "is_human": true, "type": "Position", "ts": 1770738195, "px": 220.55, "py": 371.47}, {"player": "409f0ae7-a4cf-4005-9c04-1f8fb2059a12", "is_human": true, "type": "Loot", "ts": 1770738200, "px": 218.63, "py": 365.49}, {"player": "409f0ae7-a4cf-4005-9c04-1f8fb2059a12", "is_human": true, "type": "Loot", "ts": 1770738200, "px": 218.63, "py": 365.49}, {"player": "409f0ae7-a4cf-4005-9c04-1f8fb2059a12", "is_human": true, "type": "Position", "ts": 1770738200, "px": 218.63, "py": 365.49}, {"player": "409f0ae7-a4cf-4005-9c04-1f8fb2059a12", "is_human": true, "type": "Loot", "ts": 1770738201, "px": 218.63, "py": 365.49}, {"player": "409f0ae7-a4cf-4005-9c04-1f8fb2059a12", "is_human": true, "type": "Position", "ts": 1770738205, "px": 227.79, "py": 359.75}, {"player": "409f0ae7-a4cf-4005-9c04-1f8fb2059a12", "is_human": true, "type": "Position", "ts": 1770738210, "px": 257.72, "py": 366.22}, {"player": "409f0ae7-a4cf-4005-9c04-1f8fb2059a12", "is_human": true, "type": "Position", "ts": 1770738215, "px": 280.45, "py": 376.29}, {"player": "409f0ae7-a4cf-4005-9c04-1f8fb2059a12", "is_human": true, "type": "Loot", "ts": 1770738219, "px": 280.45, "py": 378.85}, {"player": "409f0ae7-a4cf-4005-9c04-1f8fb2059a12", "is_human": true, "type": "Loot", "ts": 1770738219, "px": 280.45, "py": 378.85}, {"player": "409f0ae7-a4cf-4005-9c04-1f8fb2059a12", "is_human": true, "type": "Position", "ts": 1770738220, "px": 280.45, "py": 378.85}, {"player": "409f0ae7-a4cf-4005-9c04-1f8fb2059a12", "is_human": true, "type": "Position", "ts": 1770738225, "px": 297.09, "py": 395.57}, {"player": "409f0ae7-a4cf-4005-9c04-1f8fb2059a12", "is_human": true, "type": "Position", "ts": 1770738230, "px": 283.59, "py": 419.09}, {"player": "409f0ae7-a4cf-4005-9c04-1f8fb2059a12", "is_human": true, "type": "Position", "ts": 1770738235, "px": 283.45, "py": 425.16}, {"player": "409f0ae7-a4cf-4005-9c04-1f8fb2059a12", "is_human": true, "type": "Position", "ts": 1770738245, "px": 277.83, "py": 436.37}, {"player": "409f0ae7-a4cf-4005-9c04-1f8fb2059a12", "is_human": true, "type": "Loot", "ts": 1770738251, "px": 277.55, "py": 437.0}, {"player": "409f0ae7-a4cf-4005-9c04-1f8fb2059a12", "is_human": true, "type": "Position", "ts": 1770738255, "px": 294.2, "py": 446.51}, {"player": "409f0ae7-a4cf-4005-9c04-1f8fb2059a12", "is_human": true, "type": "Position", "ts": 1770738265, "px": 277.68, "py": 440.14}, {"player": "409f0ae7-a4cf-4005-9c04-1f8fb2059a12", "is_human": true, "type": "Position", "ts": 1770738270, "px": 265.33, "py": 455.12}, {"player": "409f0ae7-a4cf-4005-9c04-1f8fb2059a12", "is_human": true, "type": "Position", "ts": 1770738275, "px": 270.68, "py": 456.39}, {"player": "409f0ae7-a4cf-4005-9c04-1f8fb2059a12", "is_human": true, "type": "Position", "ts": 1770738280, "px": 272.67, "py": 467.37}, {"player": "409f0ae7-a4cf-4005-9c04-1f8fb2059a12", "is_human": true, "type": "Position", "ts": 1770738286, "px": 282.0, "py": 473.32}, {"player": "409f0ae7-a4cf-4005-9c04-1f8fb2059a12", "is_human": true, "type": "BotKilled", "ts": 1770738289, "px": 287.46, "py": 476.83}, {"player": "409f0ae7-a4cf-4005-9c04-1f8fb2059a12", "is_human": true, "type": "Position", "ts": 1770738291, "px": 287.61, "py": 476.8}], "humans_count": 1, "bots_count": 0, "events_count": 59}