{"match_id": "6bf911c3-8d92-48e0-a0e9-8059455dc55a.nakama-0", "map_id": "AmbroseValley", "date": "February 10", "events": [{"player": "a031639f-5ede-4265-b884-4616b9f7975b", "is_human": true, "type": "Position", "ts": 1770764416, "px": 103.68, "py": 896.58}, {"player": "a031639f-5ede-4265-b884-4616b9f7975b", "is_human": true, "type": "Position", "ts": 1770764482, "px": 109.6, "py": 895.02}, {"player": "a031639f-5ede-4265-b884-4616b9f7975b", "is_human": true, "type": "Position", "ts": 1770764487, "px": 135.04, "py": 904.48}, {"player": "a031639f-5ede-4265-b884-4616b9f7975b", "is_human": true, "type": "Position", "ts": 1770764492, "px": 151.55, "py": 913.47}, {"player": "a031639f-5ede-4265-b884-4616b9f7975b", "is_human": true, "type": "Position", "ts": 1770764497, "px": 168.6, "py": 909.88}, {"player": "a031639f-5ede-4265-b884-4616b9f7975b", "is_human": true, "type": "Position", "ts": 1770764502, "px": 187.95, "py": 900.92}, {"player": "a031639f-5ede-4265-b884-4616b9f7975b", "is_human": true, "type": "Position", "ts": 1770764507, "px": 210.09, "py": 891.1}, {"player": "a031639f-5ede-4265-b884-4616b9f7975b", "is_human": true, "type": "Position", "ts": 1770764512, "px": 215.14, "py": 890.36}, {"player": "a031639f-5ede-4265-b884-4616b9f7975b", "is_human": true, "type": "Position", "ts": 1770764517, "px": 221.75, "py": 887.77}, {"player": "a031639f-5ede-4265-b884-4616b9f7975b", "is_human": true, "type": "Position", "ts": 1770764522, "px": 240.97, "py": 877.65}, {"player": "a031639f-5ede-4265-b884-4616b9f7975b", "is_human": true, "type": "Position", "ts": 1770764527, "px": 258.03, "py": 870.62}, {"player": "a031639f-5ede-4265-b884-4616b9f7975b", "is_human": true, "type": "Position", "ts": 1770764532, "px": 263.7, "py": 864.03}, {"player": "a031639f-5ede-4265-b884-4616b9f7975b", "is_human": true, "type": "Position", "ts": 1770764557, "px": 269.15, "py": 867.07}, {"player": "a031639f-5ede-4265-b884-4616b9f7975b", "is_human": true, "type": "Position", "ts": 1770764562, "px": 265.34, "py": 873.62}, {"player": "a031639f-5ede-4265-b884-4616b9f7975b", "is_human": true, "type": "Position", "ts": 1770764572, "px": 257.75, "py": 861.94}, {"player": "a031639f-5ede-4265-b884-4616b9f7975b", "is_human": true, "type": "Position", "ts": 1770764577, "px": 254.74, "py": 842.8}, {"player": "a031639f-5ede-4265-b884-4616b9f7975b", "is_human": true, "type": "Position", "ts": 1770764582, "px": 274.75, "py": 820.45}, {"player": "a031639f-5ede-4265-b884-4616b9f7975b", "is_human": true, "type": "Position", "ts": 1770764587, "px": 293.28, "py": 807.9}, {"player": "a031639f-5ede-4265-b884-4616b9f7975b", "is_human": true, "type": "Position", "ts": 1770764592, "px": 300.88, "py": 801.74}, {"player": "a031639f-5ede-4265-b884-4616b9f7975b", "is_human": true, "type": "Position", "ts": 1770764597, "px": 302.08, "py": 799.09}, {"player": "a031639f-5ede-4265-b884-4616b9f7975b", "is_human": true, "type": "Position", "ts": 1770764607, "px": 303.75, "py": 798.32}, {"player": "a031639f-5ede-4265-b884-4616b9f7975b", "is_human": true, "type": "Position", "ts": 1770764612, "px": 310.41, "py": 801.06}, {"player": "a031639f-5ede-4265-b884-4616b9f7975b", "is_human": true, "type": "Loot", "ts": 1770764616, "px": 308.19, "py": 810.93}, {"player": "a031639f-5ede-4265-b884-4616b9f7975b", "is_human": true, "type": "Position", "ts": 1770764617, "px": 308.19, "py": 810.93}, {"player": "a031639f-5ede-4265-b884-4616b9f7975b", "is_human": true, "type": "Position", "ts": 1770764622, "px": 302.9, "py": 830.71}, {"player": "a031639f-5ede-4265-b884-4616b9f7975b", "is_human": true, "type": "Position", "ts": 1770764628, "px": 316.99, "py": 857.63}, {"player": "a031639f-5ede-4265-b884-4616b9f7975b", "is_human": true, "type": "Position", "ts": 1770764633, "px": 352.72, "py": 864.77}, {"player": "a031639f-5ede-4265-b884-4616b9f7975b", "is_human": true, "type": "Position", "ts": 1770764638, "px": 388.04, "py": 864.86}, {"player": "a031639f-5ede-4265-b884-4616b9f7975b", "is_human": true, "type": "Position", "ts": 1770764643, "px": 406.82, "py": 867.67}, {"player": "a031639f-5ede-4265-b884-4616b9f7975b", "is_human": true, "type": "Position", "ts": 1770764733, "px": 423.81, "py": 875.77}, {"player": "a031639f-5ede-4265-b884-4616b9f7975b", "is_human": true, "type": "Position", "ts": 1770764738, "px": 417.65, "py": 874.67}, {"player": "a031639f-5ede-4265-b884-4616b9f7975b", "is_human": true, "type": "Position", "ts": 1770764743, "px": 401.26, "py": 869.66}, {"player": "a031639f-5ede-4265-b884-4616b9f7975b", "is_human": true, "type": "Position", "ts": 1770764748, "px": 379.59, "py": 870.02}, {"player": "a031639f-5ede-4265-b884-4616b9f7975b", "is_human": true, "type": "Position", "ts": 1770764753, "px": 358.14, "py": 868.02}, {"player": "a031639f-5ede-4265-b884-4616b9f7975b", "is_human": true, "type": "Position", "ts": 1770764758, "px": 336.61, "py": 864.51}, {"player": "a031639f-5ede-4265-b884-4616b9f7975b", "is_human": true, "type": "Position", "ts": 1770764763, "px": 315.08, "py": 865.85}, {"player": "a031639f-5ede-4265-b884-4616b9f7975b", "is_human": true, "type": "Position", "ts": 1770764768, "px": 281.27, "py": 870.08}, {"player": "a031639f-5ede-4265-b884-4616b9f7975b", "is_human": true, "type": "Position", "ts": 1770764773, "px": 258.7, "py": 878.74}, {"player": "a031639f-5ede-4265-b884-4616b9f7975b", "is_human": true, "type": "Position", "ts": 1770764778, "px": 239.65, "py": 889.53}, {"player": "a031639f-5ede-4265-b884-4616b9f7975b", "is_human": true, "type": "Position", "ts": 1770764783, "px": 221.59, "py": 891.35}, {"player": "a031639f-5ede-4265-b884-4616b9f7975b", "is_human": true, "type": "Position", "ts": 1770764788, "px": 204.46, "py": 891.82}, {"player": "a031639f-5ede-4265-b884-4616b9f7975b", "is_human": true, "type": "Position", "ts": 1770764793, "px": 199.09, "py": 898.64}, {"player": "a031639f-5ede-4265-b884-4616b9f7975b", "is_human": true, "type": "Position", "ts": 1770764803, "px": 200.44, "py": 904.1}, {"player": "a031639f-5ede-4265-b884-4616b9f7975b", "is_human": true, "type": "Position", "ts": 1770764809, "px": 206.57, "py": 907.96}, {"player": "a031639f-5ede-4265-b884-4616b9f7975b", "is_human": true, "type": "Position", "ts": 1770764814, "px": 228.23, "py": 890.26}, {"player": "a031639f-5ede-4265-b884-4616b9f7975b", "is_human": true, "type": "Position", "ts": 1770764819, "px": 252.72, "py": 862.89}, {"player": "a031639f-5ede-4265-b884-4616b9f7975b", "is_human": true, "type": "Position", "ts": 1770764824, "px": 259.86, "py": 862.52}, {"player": "a031639f-5ede-4265-b884-4616b9f7975b", "is_human": true, "type": "Position", "ts": 1770764879, "px": 258.06, "py": 856.2}, {"player": "a031639f-5ede-4265-b884-4616b9f7975b", "is_human": true, "type": "Position", "ts": 1770764884, "px": 253.04, "py": 840.2}, {"player": "a031639f-5ede-4265-b884-4616b9f7975b", "is_human": true, "type": "Position", "ts": 1770764889, "px": 238.5, "py": 836.68}, {"player": "a031639f-5ede-4265-b884-4616b9f7975b", "is_human": true, "type": "Position", "ts": 1770764894, "px": 229.05, "py": 837.24}, {"player": "a031639f-5ede-4265-b884-4616b9f7975b", "is_human": true, "type": "Position", "ts": 1770764899, "px": 222.31, "py": 849.08}, {"player": "a031639f-5ede-4265-b884-4616b9f7975b", "is_human": true, "type": "Position", "ts": 1770764904, "px": 207.41, "py": 856.3}, {"player": "a031639f-5ede-4265-b884-4616b9f7975b", "is_human": true, "type": "Position", "ts": 1770764949, "px": 211.01, "py": 857.42}, {"player": "a031639f-5ede-4265-b884-4616b9f7975b", "is_human": true, "type": "Position", "ts": 1770764969, "px": 209.86, "py": 857.08}, {"player": "a031639f-5ede-4265-b884-4616b9f7975b", "is_human": true, "type": "BotKilled", "ts": 1770764977, "px": 209.86, "py": 857.08}], "humans_count": 1, "bots_count": 0, "events_count": 56}