{"match_id": "d11fb223-921a-41e2-a0b0-17e588dcbdba.nakama-0", "map_id": "AmbroseValley", "date": "February 10", "events": [{"player": "e7ac0138-4d80-4400-9141-461daa6be8ae", "is_human": true, "type": "Position", "ts": 1770728805, "px": 78.59, "py": 890.42}, {"player": "e7ac0138-4d80-4400-9141-461daa6be8ae", "is_human": true, "type": "Position", "ts": 1770728815, "px": 79.72, "py": 889.84}, {"player": "e7ac0138-4d80-4400-9141-461daa6be8ae", "is_human": true, "type": "Position", "ts": 1770728820, "px": 113.88, "py": 875.64}, {"player": "e7ac0138-4d80-4400-9141-461daa6be8ae", "is_human": true, "type": "Position", "ts": 1770728825, "px": 140.79, "py": 865.24}, {"player": "e7ac0138-4d80-4400-9141-461daa6be8ae", "is_human": true, "type": "Position", "ts": 1770728830, "px": 154.4, "py": 862.52}, {"player": "e7ac0138-4d80-4400-9141-461daa6be8ae", "is_human": true, "type": "Loot", "ts": 1770728832, "px": 163.27, "py": 859.69}, {"player": "e7ac0138-4d80-4400-9141-461daa6be8ae", "is_human": true, "type": "Position", "ts": 1770728835, "px": 167.39, "py": 846.44}, {"player": "e7ac0138-4d80-4400-9141-461daa6be8ae", "is_human": true, "type": "Loot", "ts": 1770728837, "px": 179.12, "py": 840.33}, {"player": "e7ac0138-4d80-4400-9141-461daa6be8ae", "is_human": true, "type": "Position", "ts": 1770728840, "px": 179.21, "py": 852.03}, {"player": "e7ac0138-4d80-4400-9141-461daa6be8ae", "is_human": true, "type": "Position", "ts": 1770728845, "px": 178.24, "py": 854.57}, {"player": "e7ac0138-4d80-4400-9141-461daa6be8ae", "is_human": true, "type": "Position", "ts": 1770728850, "px": 171.29, "py": 861.24}, {"player": "e7ac0138-4d80-4400-9141-461daa6be8ae", "is_human": true, "type": "Loot", "ts": 1770728851, "px": 171.29, "py": 861.24}, {"player": "e7ac0138-4d80-4400-9141-461daa6be8ae", "is_human": true, "type": "Loot", "ts": 1770728852, "px": 171.29, "py": 861.24}, {"player": "e7ac0138-4d80-4400-9141-461daa6be8ae", "is_human": true, "type": "Position", "ts": 1770728855, "px": 173.55, "py": 867.9}, {"player": "e7ac0138-4d80-4400-9141-461daa6be8ae", "is_human": true, "type": "Position", "ts": 1770728860, "px": 190.88, "py": 871.74}, {"player": "e7ac0138-4d80-4400-9141-461daa6be8ae", "is_human": true, "type": "BotKill", "ts": 1770728864, "px": 196.32, "py": 872.77}, {"player": "e7ac0138-4d80-4400-9141-461daa6be8ae", "is_human": true, "type": "Position", "ts": 1770728865, "px": 196.32, "py": 872.77}, {"player": "e7ac0138-4d80-4400-9141-461daa6be8ae", "is_human": true, "type": "Loot", "ts": 1770728870, "px": 203.69, "py": 861.43}, {"player": "e7ac0138-4d80-4400-9141-461daa6be8ae", "is_human": true, "type": "Position", "ts": 1770728870, "px": 203.69, "py": 861.43}, {"player": "e7ac0138-4d80-4400-9141-461daa6be8ae", "is_human": true, "type": "Loot", "ts": 1770728870, "px": 203.69, "py": 861.43}, {"player": "e7ac0138-4d80-4400-9141-461daa6be8ae", "is_human": true, "type": "Position", "ts": 1770728875, "px": 209.51, "py": 854.97}, {"player": "e7ac0138-4d80-4400-9141-461daa6be8ae", "is_human": true, "type": "Position", "ts": 1770728880, "px": 222.97, "py": 863.27}, {"player": "e7ac0138-4d80-4400-9141-461daa6be8ae", "is_human": true, "type": "Loot", "ts": 1770728885, "px": 226.18, "py": 873.33}, {"player": "e7ac0138-4d80-4400-9141-461daa6be8ae", "is_human": true, "type": "Position", "ts": 1770728885, "px": 226.18, "py": 873.33}, {"player": "e7ac0138-4d80-4400-9141-461daa6be8ae", "is_human": true, "type": "Position", "ts": 1770728890, "px": 210.75, "py": 856.55}, {"player": "e7ac0138-4d80-4400-9141-461daa6be8ae", "is_human": true, "type": "Position", "ts": 1770728895, "px": 226.11, "py": 848.14}, {"player": "e7ac0138-4d80-4400-9141-461daa6be8ae", "is_human": true, "type": "Position", "ts": 1770728900, "px": 255.15, "py": 832.95}, {"player": "e7ac0138-4d80-4400-9141-461daa6be8ae", "is_human": true, "type": "Position", "ts": 1770728905, "px": 273.72, "py": 804.02}, {"player": "e7ac0138-4d80-4400-9141-461daa6be8ae", "is_human": true, "type": "Position", "ts": 1770728910, "px": 281.23, "py": 787.54}, {"player": "e7ac0138-4d80-4400-9141-461daa6be8ae", "is_human": true, "type": "Position", "ts": 1770728915, "px": 283.55, "py": 762.06}, {"player": "e7ac0138-4d80-4400-9141-461daa6be8ae", "is_human": true, "type": "Position", "ts": 1770728920, "px": 282.96, "py": 747.03}, {"player": "e7ac0138-4d80-4400-9141-461daa6be8ae", "is_human": true, "type": "Position", "ts": 1770728925, "px": 279.69, "py": 738.87}, {"player": "e7ac0138-4d80-4400-9141-461daa6be8ae", "is_human": true, "type": "Position", "ts": 1770728930, "px": 290.5, "py": 769.95}, {"player": "e7ac0138-4d80-4400-9141-461daa6be8ae", "is_human": true, "type": "Loot", "ts": 1770728935, "px": 305.93, "py": 783.78}, {"player": "e7ac0138-4d80-4400-9141-461daa6be8ae", "is_human": true, "type": "Position", "ts": 1770728935, "px": 305.9, "py": 783.87}, {"player": "e7ac0138-4d80-4400-9141-461daa6be8ae", "is_human": true, "type": "Position", "ts": 1770728940, "px": 300.84, "py": 799.81}, {"player": "e7ac0138-4d80-4400-9141-461daa6be8ae", "is_human": true, "type": "Position", "ts": 1770728946, "px": 312.66, "py": 799.88}, {"player": "e7ac0138-4d80-4400-9141-461daa6be8ae", "is_human": true, "type": "Position", "ts": 1770728951, "px": 340.77, "py": 799.45}, {"player": "e7ac0138-4d80-4400-9141-461daa6be8ae", "is_human": true, "type": "Position", "ts": 1770728956, "px": 376.12, "py": 795.8}, {"player": "e7ac0138-4d80-4400-9141-461daa6be8ae", "is_human": true, "type": "Position", "ts": 1770728961, "px": 402.74, "py": 796.19}, {"player": "e7ac0138-4d80-4400-9141-461daa6be8ae", "is_human": true, "type": "Loot", "ts": 1770728963, "px": 400.42, "py": 803.62}, {"player": "e7ac0138-4d80-4400-9141-461daa6be8ae", "is_human": true, "type": "Position", "ts": 1770728966, "px": 405.04, "py": 808.52}, {"player": "e7ac0138-4d80-4400-9141-461daa6be8ae", "is_human": true, "type": "Loot", "ts": 1770728970, "px": 414.31, "py": 811.21}, {"player": "e7ac0138-4d80-4400-9141-461daa6be8ae", "is_human": true, "type": "Position", "ts": 1770728971, "px": 415.61, "py": 810.51}, {"player": "e7ac0138-4d80-4400-9141-461daa6be8ae", "is_human": true, "type": "Loot", "ts": 1770728973, "px": 420.45, "py": 800.97}, {"player": "e7ac0138-4d80-4400-9141-461daa6be8ae", "is_human": true, "type": "Loot", "ts": 1770728973, "px": 420.45, "py": 800.97}, {"player": "e7ac0138-4d80-4400-9141-461daa6be8ae", "is_human": true, "type": "Position", "ts": 1770728976, "px": 416.22, "py": 801.09}, {"player": "e7ac0138-4d80-4400-9141-461daa6be8ae", "is_human": true, "type": "Position", "ts": 1770728981, "px": 410.39, "py": 805.21}, {"player": "e7ac0138-4d80-4400-9141-461daa6be8ae", "is_human": true, "type": "Loot", "ts": 1770728985, "px": 412.9, "py": 799.54}, {"player": "e7ac0138-4d80-4400-9141-461daa6be8ae", "is_human": true, "type": "Position", "ts": 1770728986, "px": 415.16, "py": 799.92}, {"player": "e7ac0138-4d80-4400-9141-461daa6be8ae", "is_human": true, "type": "Position", "ts": 1770728991, "px": 420.95, "py": 796.68}, {"player": "e7ac0138-4d80-4400-9141-461daa6be8ae", "is_human": true, "type": "Position", "ts": 1770728996, "px": 418.45, "py": 804.48}, {"player": "e7ac0138-4d80-4400-9141-461daa6be8ae", "is_human": true, "type": "Position", "ts": 1770729001, "px": 416.53, "py": 798.98}, {"player": "e7ac0138-4d80-4400-9141-461daa6be8ae", "is_human": true, "type": "Position", "ts": 1770729006, "px": 415.05, "py": 808.83}, {"player": "e7ac0138-4d80-4400-9141-461daa6be8ae", "is_human": true, "type": "Position", "ts": 1770729011, "px": 400.77, "py": 803.83}, {"player": "e7ac0138-4d80-4400-9141-461daa6be8ae", "is_human": true, "type": "Position", "ts": 1770729016, "px": 406.06, "py": 801.15}, {"player": "e7ac0138-4d80-4400-9141-461daa6be8ae", "is_human": true, "type": "Loot", "ts": 1770729018, "px": 406.22, "py": 805.02}, {"player": "e7ac0138-4d80-4400-9141-461daa6be8ae", "is_human": true, "type": "Position", "ts": 1770729021, "px": 410.12, "py": 807.75}, {"player": "e7ac0138-4d80-4400-9141-461daa6be8ae", "is_human": true, "type": "Position", "ts": 1770729026, "px": 411.73, "py": 804.74}, {"player": "e7ac0138-4d80-4400-9141-461daa6be8ae", "is_human": true, "type": "Position", "ts": 1770729031, "px": 412.84, "py": 811.59}, {"player": "e7ac0138-4d80-4400-9141-461daa6be8ae", "is_human": true, "type": "Position", "ts": 1770729036, "px": 411.71, "py": 809.62}, {"player": "e7ac0138-4d80-4400-9141-461daa6be8ae", "is_human": true, "type": "Position", "ts": 1770729041, "px": 425.84, "py": 813.85}, {"player": "e7ac0138-4d80-4400-9141-461daa6be8ae", "is_human": true, "type": "Position", "ts": 1770729046, "px": 431.08, "py": 813.76}, {"player": "e7ac0138-4d80-4400-9141-461daa6be8ae", "is_human": true, "type": "Position", "ts": 1770729051, "px": 459.5, "py": 799.16}, {"player": "e7ac0138-4d80-4400-9141-461daa6be8ae", "is_human": true, "type": "Position", "ts": 1770729056, "px": 467.62, "py": 779.19}, {"player": "e7ac0138-4d80-4400-9141-461daa6be8ae", "is_human": true, "type": "Position", "ts": 1770729061, "px": 472.3, "py": 778.61}, {"player": "e7ac0138-4d80-4400-9141-461daa6be8ae", "is_human": true, "type": "Loot", "ts": 1770729064, "px": 472.3, "py": 778.61}, {"player": "e7ac0138-4d80-4400-9141-461daa6be8ae", "is_human": true, "type": "Position", "ts": 1770729066, "px": 471.32, "py": 782.76}, {"player": "e7ac0138-4d80-4400-9141-461daa6be8ae", "is_human": true, "type": "BotKill", "ts": 1770729068, "px": 470.55, "py": 784.61}, {"player": "e7ac0138-4d80-4400-9141-461daa6be8ae", "is_human": true, "type": "Position", "ts": 1770729071, "px": 482.82, "py": 784.29}, {"player": "e7ac0138-4d80-4400-9141-461daa6be8ae", "is_human": true, "type": "Loot", "ts": 1770729072, "px": 483.55, "py": 784.67}, {"player": "e7ac0138-4d80-4400-9141-461daa6be8ae", "is_human": true, "type": "Loot", "ts": 1770729072, "px": 483.55, "py": 784.67}, {"player": "e7ac0138-4d80-4400-9141-461daa6be8ae", "is_human": true, "type": "Loot", "ts": 1770729073, "px": 483.55, "py": 784.67}, {"player": "e7ac0138-4d80-4400-9141-461daa6be8ae", "is_human": true, "type": "Position", "ts": 1770729076, "px": 489.77, "py": 778.55}, {"player": "e7ac0138-4d80-4400-9141-461daa6be8ae", "is_human": true, "type": "Position", "ts": 1770729081, "px": 463.63, "py": 768.37}, {"player": "e7ac0138-4d80-4400-9141-461daa6be8ae", "is_human": true, "type": "Position", "ts": 1770729086, "px": 430.17, "py": 760.16}, {"player": "e7ac0138-4d80-4400-9141-461daa6be8ae", "is_human": true, "type": "Position", "ts": 1770729091, "px": 395.54, "py": 746.68}, {"player": "e7ac0138-4d80-4400-9141-461daa6be8ae", "is_human": true, "type": "Position", "ts": 1770729096, "px": 375.56, "py": 727.37}, {"player": "e7ac0138-4d80-4400-9141-461daa6be8ae", "is_human": true, "type": "Position", "ts": 1770729101, "px": 357.44, "py": 703.73}, {"player": "e7ac0138-4d80-4400-9141-461daa6be8ae", "is_human": true, "type": "Position", "ts": 1770729106, "px": 346.63, "py": 696.54}, {"player": "e7ac0138-4d80-4400-9141-461daa6be8ae", "is_human": true, "type": "Position", "ts": 1770729116, "px": 330.57, "py": 701.75}, {"player": "e7ac0138-4d80-4400-9141-461daa6be8ae", "is_human": true, "type": "Position", "ts": 1770729122, "px": 307.76, "py": 701.12}, {"player": "e7ac0138-4d80-4400-9141-461daa6be8ae", "is_human": true, "type": "Loot", "ts": 1770729122, "px": 307.56, "py": 701.23}, {"player": "e7ac0138-4d80-4400-9141-461daa6be8ae", "is_human": true, "type": "Position", "ts": 1770729127, "px": 299.75, "py": 698.92}, {"player": "e7ac0138-4d80-4400-9141-461daa6be8ae", "is_human": true, "type": "Position", "ts": 1770729137, "px": 288.24, "py": 730.63}, {"player": "e7ac0138-4d80-4400-9141-461daa6be8ae", "is_human": true, "type": "Position", "ts": 1770729142, "px": 263.35, "py": 757.71}, {"player": "e7ac0138-4d80-4400-9141-461daa6be8ae", "is_human": true, "type": "Position", "ts": 1770729147, "px": 246.73, "py": 770.33}, {"player": "e7ac0138-4d80-4400-9141-461daa6be8ae", "is_human": true, "type": "Position", "ts": 1770729152, "px": 249.26, "py": 766.82}], "humans_count": 1, "bots_count": 0, "events_count": 88}