{"match_id": "fbe1944e-bf85-4fd9-8ce7-4d8134f2d320.nakama-0", "map_id": "AmbroseValley", "date": "February 10", "events": [{"player": "24bd210d-3b53-4f06-acf1-a0e0385641b6", "is_human": true, "type": "Position", "ts": 1770722920, "px": 224.38, "py": 102.69}, {"player": "24bd210d-3b53-4f06-acf1-a0e0385641b6", "is_human": true, "type": "Position", "ts": 1770722950, "px": 228.69, "py": 109.54}, {"player": "24bd210d-3b53-4f06-acf1-a0e0385641b6", "is_human": true, "type": "Position", "ts": 1770722955, "px": 233.6, "py": 113.21}, {"player": "24bd210d-3b53-4f06-acf1-a0e0385641b6", "is_human": true, "type": "Position", "ts": 1770722960, "px": 239.5, "py": 122.54}, {"player": "24bd210d-3b53-4f06-acf1-a0e0385641b6", "is_human": true, "type": "Position", "ts": 1770722965, "px": 250.18, "py": 127.35}, {"player": "24bd210d-3b53-4f06-acf1-a0e0385641b6", "is_human": true, "type": "Loot", "ts": 1770722965, "px": 250.18, "py": 127.35}, {"player": "24bd210d-3b53-4f06-acf1-a0e0385641b6", "is_human": true, "type": "Position", "ts": 1770722970, "px": 245.2, "py": 139.47}, {"player": "24bd210d-3b53-4f06-acf1-a0e0385641b6", "is_human": true, "type": "Loot", "ts": 1770722974, "px": 246.62, "py": 141.45}, {"player": "24bd210d-3b53-4f06-acf1-a0e0385641b6", "is_human": true, "type": "Position", "ts": 1770722985, "px": 247.89, "py": 133.5}, {"player": "24bd210d-3b53-4f06-acf1-a0e0385641b6", "is_human": true, "type": "Position", "ts": 1770722991, "px": 229.78, "py": 129.18}, {"player": "24bd210d-3b53-4f06-acf1-a0e0385641b6", "is_human": true, "type": "Loot", "ts": 1770722995, "px": 220.97, "py": 130.07}, {"player": "24bd210d-3b53-4f06-acf1-a0e0385641b6", "is_human": true, "type": "Position", "ts": 1770722996, "px": 220.0, "py": 128.91}, {"player": "24bd210d-3b53-4f06-acf1-a0e0385641b6", "is_human": true, "type": "Position", "ts": 1770723021, "px": 222.04, "py": 128.53}, {"player": "24bd210d-3b53-4f06-acf1-a0e0385641b6", "is_human": true, "type": "Position", "ts": 1770723026, "px": 235.75, "py": 141.13}, {"player": "24bd210d-3b53-4f06-acf1-a0e0385641b6", "is_human": true, "type": "Position", "ts": 1770723031, "px": 238.22, "py": 148.44}, {"player": "24bd210d-3b53-4f06-acf1-a0e0385641b6", "is_human": true, "type": "Loot", "ts": 1770723031, "px": 238.22, "py": 148.44}, {"player": "24bd210d-3b53-4f06-acf1-a0e0385641b6", "is_human": true, "type": "Loot", "ts": 1770723031, "px": 238.22, "py": 148.44}, {"player": "24bd210d-3b53-4f06-acf1-a0e0385641b6", "is_human": true, "type": "Position", "ts": 1770723041, "px": 242.37, "py": 146.4}, {"player": "24bd210d-3b53-4f06-acf1-a0e0385641b6", "is_human": true, "type": "Loot", "ts": 1770723043, "px": 242.37, "py": 146.4}, {"player": "24bd210d-3b53-4f06-acf1-a0e0385641b6", "is_human": true, "type": "Position", "ts": 1770723046, "px": 245.81, "py": 151.93}, {"player": "24bd210d-3b53-4f06-acf1-a0e0385641b6", "is_human": true, "type": "Loot", "ts": 1770723049, "px": 254.84, "py": 150.5}, {"player": "24bd210d-3b53-4f06-acf1-a0e0385641b6", "is_human": true, "type": "Position", "ts": 1770723051, "px": 258.74, "py": 160.03}, {"player": "24bd210d-3b53-4f06-acf1-a0e0385641b6", "is_human": true, "type": "Position", "ts": 1770723056, "px": 275.84, "py": 189.38}, {"player": "24bd210d-3b53-4f06-acf1-a0e0385641b6", "is_human": true, "type": "Position", "ts": 1770723061, "px": 277.51, "py": 202.23}, {"player": "24bd210d-3b53-4f06-acf1-a0e0385641b6", "is_human": true, "type": "Loot", "ts": 1770723062, "px": 277.51, "py": 202.23}, {"player": "24bd210d-3b53-4f06-acf1-a0e0385641b6", "is_human": true, "type": "Position", "ts": 1770723066, "px": 294.8, "py": 196.56}, {"player": "24bd210d-3b53-4f06-acf1-a0e0385641b6", "is_human": true, "type": "Position", "ts": 1770723071, "px": 322.41, "py": 187.82}, {"player": "24bd210d-3b53-4f06-acf1-a0e0385641b6", "is_human": true, "type": "Position", "ts": 1770723076, "px": 353.85, "py": 185.87}, {"player": "24bd210d-3b53-4f06-acf1-a0e0385641b6", "is_human": true, "type": "Position", "ts": 1770723081, "px": 382.57, "py": 193.74}, {"player": "24bd210d-3b53-4f06-acf1-a0e0385641b6", "is_human": true, "type": "Position", "ts": 1770723086, "px": 380.61, "py": 194.08}, {"player": "24bd210d-3b53-4f06-acf1-a0e0385641b6", "is_human": true, "type": "Position", "ts": 1770723091, "px": 420.13, "py": 208.09}, {"player": "24bd210d-3b53-4f06-acf1-a0e0385641b6", "is_human": true, "type": "Position", "ts": 1770723096, "px": 436.55, "py": 210.68}, {"player": "24bd210d-3b53-4f06-acf1-a0e0385641b6", "is_human": true, "type": "Position", "ts": 1770723101, "px": 453.07, "py": 218.67}, {"player": "24bd210d-3b53-4f06-acf1-a0e0385641b6", "is_human": true, "type": "BotKilled", "ts": 1770723106, "px": 457.03, "py": 222.13}, {"player": "24bd210d-3b53-4f06-acf1-a0e0385641b6", "is_human": true, "type": "Position", "ts": 1770723106, "px": 457.03, "py": 222.13}], "humans_count": 1, "bots_count": 0, "events_count": 35}